setup.cfg
setup.py
cp_redis.egg-info/PKG-INFO
cp_redis.egg-info/SOURCES.txt
cp_redis.egg-info/dependency_links.txt
cp_redis.egg-info/entry_points.txt
cp_redis.egg-info/not-zip-safe
cp_redis.egg-info/requires.txt
cp_redis.egg-info/top_level.txt
cpredis/__init__.py
cpredis/rediser_cache.py