Metadata-Version: 1.0
Name: cp-redis
Version: 0.0.1
Summary: This is Carpool Project subpackage: cp cp-redis
Home-page: UNKNOWN
Author: petergra
Author-email: lvpet@esquel.com
License: MIT
Platform: UNKNOWN
